pkgF12/__init__.py
pkgF12/main.py
pkgF12-0.5.dist-info/LICENSE.txt
pkgF12-0.5.dist-info/METADATA
pkgF12-0.5.dist-info/WHEEL
pkgF12-0.5.dist-info/top_level.txt
pkgF12-0.5.dist-info/RECORD
