Metadata-Version: 2.1
Name: pkgF12
Version: 0.5
Summary: This Is pkgF1 desc
Home-page: UNKNOWN
Author: abc
Author-email: UNKNOWN
License: MIT
Platform: UNKNOWN
